TPLParser/__init__.py
TPLParser/cli.py
TPLParser/tpl_reader.py
TPLParser/utils.py
tpl_parser-1.0.1.dist-info/LICENSE
tpl_parser-1.0.1.dist-info/METADATA
tpl_parser-1.0.1.dist-info/WHEEL
tpl_parser-1.0.1.dist-info/entry_points.txt
tpl_parser-1.0.1.dist-info/top_level.txt
tpl_parser-1.0.1.dist-info/RECORD
