Metadata-Version: 2.1
Name: tpl-parser
Version: 1.0.1
Summary: A Python package to parse Photoshop TPL files and extract data into JSON format.
Home-page: https://github.com/DavyJonesCodes/TPLParserPy
Author: Dev Jones
Author-email: devjonescodes@gmail.com
Classifier: Programming Language :: Python :: 3
Classifier: License :: Free for non-commercial use
Classifier: Operating System :: OS Independent
Requires-Python: >=3.6
License-File: LICENSE
